__init__.py
battlenet_base/__init__.py
battlenet_base/client.py
battlenet_base/py.typed
battlenet_base/api/__init__.py
battlenet_base/api/oauth.py
battlenet_base/cache/__init__.py
battlenet_base/cache/base.py
battlenet_base/cache/mongo.py
battlenet_base/cache/mysql.py
battlenet_base/cache/postgresql.py
battlenet_base/cache/redis.py
battlenet_base/cache/sqlite.py
battlenet_base/utils/__init__.py
battlenet_base/utils/constants.py
battlenet_base/utils/decorators.py
battlenet_base/utils/exceptions.py
battlenet_base/utils/utils.py
battlenet_client/__init__.py
battlenet_client/client.py
battlenet_client/decorators.py
battlenet_client/oauth.py
battlenet_client/py.typed
battlenet_client/utils.py
battlenet_client/api/__init__.py
battlenet_client/api/oauth.py
battlenet_client/cache/__init__.py
battlenet_client/cache/base.py
battlenet_client/cache/mongo.py
battlenet_client/cache/mysql.py
battlenet_client/cache/postgresql.py
battlenet_client/cache/redis.py
battlenet_client/cache/sqlite.py
battlenet_client/utils/__init__.py
battlenet_client/utils/constants.py
battlenet_client/utils/decorators.py
battlenet_client/utils/exceptions.py
battlenet_client/utils/utils.py
battlenet_client-5.0.6.dist-info/licenses/LICENSE
battlenet_client-5.0.6.dist-info/METADATA
battlenet_client-5.0.6.dist-info/WHEEL
battlenet_client-5.0.6.dist-info/top_level.txt
battlenet_client-5.0.6.dist-info/RECORD
