Metadata-Version: 2.4
Name: battlenet-client
Version: 5.0.6
Summary: Package provides easy access to Blizzard Game APIs
Author-email: David 'Gahd' Couples <gahdania@gahd.io>
License-Expression: GPL-3.0-or-later
Project-URL: Homepage, https://gitlab.com/battlenet-client/api/battlene-clientt
Project-URL: Bug Tracker, https://gitlab.com/battlenet-client/api/battlenet-client/issues
Classifier: Development Status :: 3 - Alpha
Classifier: Programming Language :: Python :: 3
Classifier: Operating System :: OS Independent
Requires-Python: >=3.7
License-File: LICENSE
Provides-Extra: dev
Requires-Dist: python-decouple; extra == "dev"
Requires-Dist: pytest; extra == "dev"
Requires-Dist: oauthlib>=3.2.2; extra == "dev"
Requires-Dist: requests_oauthlib; extra == "dev"
Requires-Dist: requests; extra == "dev"
Provides-Extra: client
Requires-Dist: oic>=1.6.1; extra == "client"
Requires-Dist: oauthlib>=3.2.2; extra == "client"
Requires-Dist: requests_oauthlib; extra == "client"
Requires-Dist: requests; extra == "client"
Dynamic: license-file
